tests/__init__.py
tests/test_hostdetail.py
tests/test_hostlist.py
tests/test_search_redirect.py
wecmdbsrv/__init__.py
wecmdbsrv/views/__init__.py
wecmdbsrv/views/basic.py
wecmdbsrv/views/host.py
wecmdbsrv/views/oauth.py
wecmdbsrv_cfomp-1.2.2.dist-info/LICENSE
wecmdbsrv_cfomp-1.2.2.dist-info/METADATA
wecmdbsrv_cfomp-1.2.2.dist-info/WHEEL
wecmdbsrv_cfomp-1.2.2.dist-info/top_level.txt
wecmdbsrv_cfomp-1.2.2.dist-info/RECORD
