Metadata-Version: 2.1
Name: wecmdbsrv-cfomp
Version: 1.2.2
Summary: Wxwork callback service for HOST CMDB
Author: chenhp
Author-email: chenhp@shchinaforutne.com
License-File: LICENSE
Requires-Dist: elasticsearch <7.18.0,>=7.17.0
Requires-Dist: Flask >=2.1.1
Requires-Dist: IPy >=1.01
Requires-Dist: setuptools >=49.2.1
Requires-Dist: Werkzeug >=2.0.1
Requires-Dist: xmltodict >=0.12.0
Requires-Dist: weworkapi-cfomp >=1.1.4
Requires-Dist: gunicorn >=20.1.0
